slide_captcha/__init__.py
slide_captcha/slide.py
slide_captcha-0.1.0.dist-info/METADATA
slide_captcha-0.1.0.dist-info/WHEEL
slide_captcha-0.1.0.dist-info/RECORD
